{
	"HEADER": {
		"FILE_ID": 144,
		"CRC": "B8768558",
		"REGISTRATION_BLOCK": [
			{
				"ID": 144,
				"UNK1": 51853,
				"UNK2": 0,
				"UNK3": 0,
				"UNK4": 103,
				"UNK5": 1200,
				"UNK6": 102,
				"UNK7": 2200,
				"STRING": "df04"
			}
		],
		"FUNS": [
			"FuncFal_df04"
		],
		"BLOCK_2_REGISTRATION": [
			{
				"TYPE": 3,
				"STRING": "df05"
			}
		]
	},
	"COMMANDS": [
		[
			{
				"LABEL": "0x78",
				"TYPE": "GETF",
				"U32": [
					41
				]
			},
			{
				"LABEL": "0x80",
				"TYPE": "EQ",
				"U32": [
					1
				]
			},
			{
				"LABEL": "0x88",
				"TYPE": "GETF",
				"U32": [
					42
				]
			},
			{
				"LABEL": "0x90",
				"TYPE": "EQ",
				"U32": [
					0
				]
			},
			{
				"LABEL": "0x98",
				"TYPE": "LAND"
			},
			{
				"LABEL": "0x9a",
				"TYPE": "JZ",
				"JUMP_TO_LABEL": "0x1636"
			},
			{
				"LABEL": "0xa0",
				"TYPE": "DUP",
				"U32": [
					42,
					1
				]
			},
			{
				"LABEL": "0xae",
				"TYPE": "SWAP2"
			},
			{
				"LABEL": "0xb0",
				"TYPE": "SETF"
			},
			{
				"LABEL": "0xb2",
				"TYPE": "POP"
			},
			{
				"LABEL": "0xb4",
				"TYPE": "SetWeather",
				"U32": [
					2
				]
			},
			{
				"LABEL": "0xbc",
				"TYPE": "DateHide",
				"U32": [
					1
				]
			},
			{
				"LABEL": "0xc4",
				"TYPE": "TimeHide",
				"U32": [
					1
				]
			},
			{
				"LABEL": "0xcc",
				"TYPE": "FadeBGtoSetBG",
				"U32": [
					2360,
					1
				]
			},
			{
				"LABEL": "0xda",
				"TYPE": "Wait",
				"U32": [
					500
				]
			},
			{
				"LABEL": "0xe2",
				"TYPE": "SkipDisable",
				"U32": [
					1
				]
			},
			{
				"LABEL": "0xea",
				"TYPE": "MoveChar",
				"U32": [
					197,
					1,
					2
				]
			},
			{
				"LABEL": "0xfe",
				"TYPE": "Wait",
				"U32": [
					2500
				]
			},
			{
				"LABEL": "0x106",
				"TYPE": "HideChar",
				"U32": [
					1,
					1
				]
			},
			{
				"LABEL": "0x114",
				"TYPE": "Wait",
				"U32": [
					1000
				]
			},
			{
				"LABEL": "0x11c",
				"TYPE": "DateShow",
				"U32": [
					1
				]
			},
			{
				"LABEL": "0x124",
				"TYPE": "TimeShow",
				"U32": [
					1
				]
			},
			{
				"LABEL": "0x12c",
				"TYPE": "FadeBGtoSetBG",
				"U32": [
					150,
					1
				]
			},
			{
				"LABEL": "0x13a",
				"TYPE": "BGMPlay",
				"U32": [
					9
				]
			},
			{
				"LABEL": "0x142",
				"TYPE": "Wait",
				"U32": [
					1500
				]
			},
			{
				"LABEL": "0x14a",
				"TYPE": "NewPage"
			},
			{
				"LABEL": "0x14c",
				"TYPE": "Text",
				"STRING": [
					"フォルテールを肩に担ぎ、この街唯一の駅へと向かって",
					"いる。"
				]
			},
			{
				"LABEL": "0x15e",
				"TYPE": "KeyWait"
			},
			{
				"LABEL": "0x160",
				"TYPE": "NewPage"
			},
			{
				"LABEL": "0x162",
				"TYPE": "Text",
				"STRING": [
					"それは海と山に囲まれたピオーヴァの街と外とを結ぶ、",
					"唯一の陸路だった。"
				]
			},
			{
				"LABEL": "0x174",
				"TYPE": "KeyWait"
			},
			{
				"LABEL": "0x176",
				"TYPE": "NewPage"
			},
			{
				"LABEL": "0x178",
				"TYPE": "Text",
				"STRING": [
					"とはいえ僕は、三年間この街から出たことはなかったか",
					"ら、自らが利用することもなかった。"
				]
			},
			{
				"LABEL": "0x18a",
				"TYPE": "KeyWait"
			},
			{
				"LABEL": "0x18c",
				"TYPE": "NewPage"
			},
			{
				"LABEL": "0x18e",
				"TYPE": "Text",
				"STRING": [
					"今日のように、ファルさんやアルを迎えに行くという用",
					"事でもなければ、わざわざ街の外れにある駅まで行くこ",
					"ともない。"
				]
			},
			{
				"LABEL": "0x1aa",
				"TYPE": "KeyWait"
			},
			{
				"LABEL": "0x1ac",
				"TYPE": "TextHide"
			},
			{
				"LABEL": "0x1ae",
				"TYPE": "BlackOut",
				"U32": [
					1
				]
			},
			{
				"LABEL": "0x1b6",
				"TYPE": "Wait",
				"U32": [
					1000
				]
			},
			{
				"LABEL": "0x1be",
				"TYPE": "AddMin",
				"U32": [
					15
				]
			},
			{
				"LABEL": "0x1c6",
				"TYPE": "FadeBGtoSetBG",
				"U32": [
					190,
					1
				]
			},
			{
				"LABEL": "0x1d4",
				"TYPE": "Wait",
				"U32": [
					1500
				]
			},
			{
				"LABEL": "0x1dc",
				"TYPE": "NewPage"
			},
			{
				"LABEL": "0x1de",
				"TYPE": "Text",
				"STRING": [
					"着いてみると、駅前はなかなかにぎわっている。"
				]
			},
			{
				"LABEL": "0x1e6",
				"TYPE": "KeyWait"
			},
			{
				"LABEL": "0x1e8",
				"TYPE": "NewPage"
			},
			{
				"LABEL": "0x1ea",
				"TYPE": "Text",
				"STRING": [
					"出口の近くでは、僕のように誰かを待つ人の姿が多く見",
					"られた。"
				]
			},
			{
				"LABEL": "0x1fc",
				"TYPE": "KeyWait"
			},
			{
				"LABEL": "0x1fe",
				"TYPE": "NewPage"
			},
			{
				"LABEL": "0x200",
				"TYPE": "Text",
				"STRING": [
					"奥のホームに列車が到着してすぐに、どこかから帰省し",
					"てきた人が出口に現れ、その再会を喜んでいる。"
				]
			},
			{
				"LABEL": "0x212",
				"TYPE": "KeyWait"
			},
			{
				"LABEL": "0x214",
				"TYPE": "NewPage"
			},
			{
				"LABEL": "0x216",
				"TYPE": "Text",
				"STRING": [
					"僕も、その中の一人と言うことになるんだろうか。"
				]
			},
			{
				"LABEL": "0x21e",
				"TYPE": "KeyWait"
			},
			{
				"LABEL": "0x220",
				"TYPE": "NewPage"
			},
			{
				"LABEL": "0x222",
				"TYPE": "Text",
				"STRING": [
					"【クリス】",
					"「もう少しかな」"
				]
			},
			{
				"LABEL": "0x234",
				"TYPE": "KeyWait"
			},
			{
				"LABEL": "0x236",
				"TYPE": "NewPage"
			},
			{
				"LABEL": "0x238",
				"TYPE": "Text",
				"STRING": [
					"まるで、大事な人を待っている時のように、時間が気に",
					"なった。"
				]
			},
			{
				"LABEL": "0x24a",
				"TYPE": "KeyWait"
			},
			{
				"LABEL": "0x24c",
				"TYPE": "NewPage"
			},
			{
				"LABEL": "0x24e",
				"TYPE": "Text",
				"STRING": [
					"その出口から出てくるのが、まるでアリエッタであるか",
					"のように、心が躍る。"
				]
			},
			{
				"LABEL": "0x260",
				"TYPE": "KeyWait"
			},
			{
				"LABEL": "0x262",
				"TYPE": "NewPage"
			},
			{
				"LABEL": "0x264",
				"TYPE": "Text",
				"STRING": [
					"……その気持ちをぐっと抑え、気持ちを落ち着かせるよ",
					"うに、深い呼吸を何度か繰り返す。"
				]
			},
			{
				"LABEL": "0x276",
				"TYPE": "KeyWait"
			},
			{
				"LABEL": "0x278",
				"TYPE": "NewPage"
			},
			{
				"LABEL": "0x27a",
				"TYPE": "Text",
				"STRING": [
					"そしてアルの手紙の一部を、都合良く思い出した。"
				]
			},
			{
				"LABEL": "0x282",
				"TYPE": "KeyWait"
			},
			{
				"LABEL": "0x284",
				"TYPE": "NewPage"
			},
			{
				"LABEL": "0x286",
				"TYPE": "Text",
				"STRING": [
					"『例えどのようなことであっても』"
				]
			},
			{
				"LABEL": "0x28e",
				"TYPE": "KeyWait"
			},
			{
				"LABEL": "0x290",
				"TYPE": "NewPage"
			},
			{
				"LABEL": "0x292",
				"TYPE": "Text",
				"STRING": [
					"それがいかにくだらない言い訳であるかを、僕は知って",
					"いる。"
				]
			},
			{
				"LABEL": "0x2a4",
				"TYPE": "KeyWait"
			},
			{
				"LABEL": "0x2a6",
				"TYPE": "NewPage"
			},
			{
				"LABEL": "0x2a8",
				"TYPE": "Text",
				"STRING": [
					"『クリス、あなたが正しいと思うことをしてください』"
				]
			},
			{
				"LABEL": "0x2b0",
				"TYPE": "KeyWait"
			},
			{
				"LABEL": "0x2b2",
				"TYPE": "NewPage"
			},
			{
				"LABEL": "0x2b4",
				"TYPE": "Text",
				"STRING": [
					"でも、それを思い出さずにはいられなかった。"
				]
			},
			{
				"LABEL": "0x2bc",
				"TYPE": "KeyWait"
			},
			{
				"LABEL": "0x2be",
				"TYPE": "TextHide"
			},
			{
				"LABEL": "0x2c0",
				"TYPE": "BlackOut",
				"U32": [
					18
				]
			},
			{
				"LABEL": "0x2c8",
				"TYPE": "Wait",
				"U32": [
					1000
				]
			},
			{
				"LABEL": "0x2d0",
				"TYPE": "SetTime",
				"U32": [
					1415
				]
			},
			{
				"LABEL": "0x2d8",
				"TYPE": "FadeBGtoSetBG",
				"U32": [
					190,
					18
				]
			},
			{
				"LABEL": "0x2e6",
				"TYPE": "MoveChar",
				"U32": [
					40,
					1,
					2
				]
			},
			{
				"LABEL": "0x2fa",
				"TYPE": "BGMPlay",
				"U32": [
					5
				]
			},
			{
				"LABEL": "0x302",
				"TYPE": "NewPage"
			},
			{
				"LABEL": "0x304",
				"TYPE": "Voice",
				"U32": [
					144001
				]
			},
			{
				"LABEL": "0x30c",
				"TYPE": "Text",
				"STRING": [
					"【ファル】",
					"「……お待たせ。列車がちょっと遅れたみたいだけど、",
					"　ごめんね」"
				]
			},
			{
				"LABEL": "0x328",
				"TYPE": "KeyWait"
			},
			{
				"LABEL": "0x32a",
				"TYPE": "NewPage"
			},
			{
				"LABEL": "0x32c",
				"TYPE": "Text",
				"STRING": [
					"【クリス】",
					"「あ……いや、大丈夫」"
				]
			},
			{
				"LABEL": "0x33e",
				"TYPE": "KeyWait"
			},
			{
				"LABEL": "0x340",
				"TYPE": "MoveChar",
				"U32": [
					42,
					1,
					1
				]
			},
			{
				"LABEL": "0x354",
				"TYPE": "NewPage"
			},
			{
				"LABEL": "0x356",
				"TYPE": "Voice",
				"U32": [
					144002
				]
			},
			{
				"LABEL": "0x35e",
				"TYPE": "Text",
				"STRING": [
					"【ファル】",
					"「……どうしたの？」"
				]
			},
			{
				"LABEL": "0x370",
				"TYPE": "KeyWait"
			},
			{
				"LABEL": "0x372",
				"TYPE": "NewPage"
			},
			{
				"LABEL": "0x374",
				"TYPE": "Text",
				"STRING": [
					"【クリス】",
					"「少し、考え事をね」"
				]
			},
			{
				"LABEL": "0x386",
				"TYPE": "KeyWait"
			},
			{
				"LABEL": "0x388",
				"TYPE": "MoveChar",
				"U32": [
					40,
					1,
					1
				]
			},
			{
				"LABEL": "0x39c",
				"TYPE": "NewPage"
			},
			{
				"LABEL": "0x39e",
				"TYPE": "Voice",
				"U32": [
					144003
				]
			},
			{
				"LABEL": "0x3a6",
				"TYPE": "Text",
				"STRING": [
					"【ファル】",
					"「ああ、癖だっけ？」"
				]
			},
			{
				"LABEL": "0x3b8",
				"TYPE": "KeyWait"
			},
			{
				"LABEL": "0x3ba",
				"TYPE": "NewPage"
			},
			{
				"LABEL": "0x3bc",
				"TYPE": "Text",
				"STRING": [
					"【クリス】",
					"「そんなところ」"
				]
			},
			{
				"LABEL": "0x3ce",
				"TYPE": "KeyWait"
			},
			{
				"LABEL": "0x3d0",
				"TYPE": "NewPage"
			},
			{
				"LABEL": "0x3d2",
				"TYPE": "Text",
				"STRING": [
					"そこまで言って、ファルさんが少し疲れているような気",
					"がした。"
				]
			},
			{
				"LABEL": "0x3e4",
				"TYPE": "KeyWait"
			},
			{
				"LABEL": "0x3e6",
				"TYPE": "NewPage"
			},
			{
				"LABEL": "0x3e8",
				"TYPE": "Text",
				"STRING": [
					"寝台列車での旅は、女の子には辛いはずだ。"
				]
			},
			{
				"LABEL": "0x3f0",
				"TYPE": "KeyWait"
			},
			{
				"LABEL": "0x3f2",
				"TYPE": "NewPage"
			},
			{
				"LABEL": "0x3f4",
				"TYPE": "Text",
				"STRING": [
					"そして手には、帰省のための荷物が入った大きめの鞄を",
					"二つ、重そうに抱えている。"
				]
			},
			{
				"LABEL": "0x406",
				"TYPE": "KeyWait"
			},
			{
				"LABEL": "0x408",
				"TYPE": "NewPage"
			},
			{
				"LABEL": "0x40a",
				"TYPE": "Text",
				"STRING": [
					"【クリス】",
					"「あ、持つよ」"
				]
			},
			{
				"LABEL": "0x41c",
				"TYPE": "KeyWait"
			},
			{
				"LABEL": "0x41e",
				"TYPE": "MoveChar",
				"U32": [
					42,
					1,
					1
				]
			},
			{
				"LABEL": "0x432",
				"TYPE": "NewPage"
			},
			{
				"LABEL": "0x434",
				"TYPE": "Voice",
				"U32": [
					144004
				]
			},
			{
				"LABEL": "0x43c",
				"TYPE": "Text",
				"STRING": [
					"【ファル】",
					"「いいの？　ありがと」"
				]
			},
			{
				"LABEL": "0x44e",
				"TYPE": "KeyWait"
			},
			{
				"LABEL": "0x450",
				"TYPE": "NewPage"
			},
			{
				"LABEL": "0x452",
				"TYPE": "Text",
				"STRING": [
					"【クリス】",
					"「もちろん。とりあえず、行こうか」"
				]
			},
			{
				"LABEL": "0x464",
				"TYPE": "KeyWait"
			},
			{
				"LABEL": "0x466",
				"TYPE": "NewPage"
			},
			{
				"LABEL": "0x468",
				"TYPE": "Text",
				"STRING": [
					"荷物の片方を受け取って肩に掛けると、相当な重さであ",
					"ることがわかった。"
				]
			},
			{
				"LABEL": "0x47a",
				"TYPE": "KeyWait"
			},
			{
				"LABEL": "0x47c",
				"TYPE": "NewPage"
			},
			{
				"LABEL": "0x47e",
				"TYPE": "Text",
				"STRING": [
					"僕の持っている方が大きいようなので、彼女の鞄はもう",
					"少し軽いとは思うんだけど……。"
				]
			},
			{
				"LABEL": "0x490",
				"TYPE": "KeyWait"
			},
			{
				"LABEL": "0x492",
				"TYPE": "NewPage"
			},
			{
				"LABEL": "0x494",
				"TYPE": "Text",
				"STRING": [
					"【クリス】",
					"「ねえ、疲れてる？」"
				]
			},
			{
				"LABEL": "0x4a6",
				"TYPE": "KeyWait"
			},
			{
				"LABEL": "0x4a8",
				"TYPE": "MoveChar",
				"U32": [
					45,
					1,
					1
				]
			},
			{
				"LABEL": "0x4bc",
				"TYPE": "NewPage"
			},
			{
				"LABEL": "0x4be",
				"TYPE": "Voice",
				"U32": [
					144005
				]
			},
			{
				"LABEL": "0x4c6",
				"TYPE": "Text",
				"STRING": [
					"【ファル】",
					"「……ん？　どうして？」"
				]
			},
			{
				"LABEL": "0x4d8",
				"TYPE": "KeyWait"
			},
			{
				"LABEL": "0x4da",
				"TYPE": "NewPage"
			},
			{
				"LABEL": "0x4dc",
				"TYPE": "Text",
				"STRING": [
					"【クリス】",
					"「そんな顔してる。寝台列車っていっても、そんなに休",
					"　めるものでもないんでしょ？」"
				]
			},
			{
				"LABEL": "0x4f8",
				"TYPE": "KeyWait"
			},
			{
				"LABEL": "0x4fa",
				"TYPE": "MoveChar",
				"U32": [
					40,
					1,
					1
				]
			},
			{
				"LABEL": "0x50e",
				"TYPE": "NewPage"
			},
			{
				"LABEL": "0x510",
				"TYPE": "Voice",
				"U32": [
					144006
				]
			},
			{
				"LABEL": "0x518",
				"TYPE": "Text",
				"STRING": [
					"【ファル】",
					"「まあね。一応眠れはするけど」"
				]
			},
			{
				"LABEL": "0x52a",
				"TYPE": "KeyWait"
			},
			{
				"LABEL": "0x52c",
				"TYPE": "NewPage"
			},
			{
				"LABEL": "0x52e",
				"TYPE": "Text",
				"STRING": [
					"【クリス】",
					"「……練習は、やめておく？」"
				]
			},
			{
				"LABEL": "0x540",
				"TYPE": "KeyWait"
			},
			{
				"LABEL": "0x542",
				"TYPE": "MoveChar",
				"U32": [
					46,
					1,
					1
				]
			},
			{
				"LABEL": "0x556",
				"TYPE": "NewPage"
			},
			{
				"LABEL": "0x558",
				"TYPE": "Voice",
				"U32": [
					144007
				]
			},
			{
				"LABEL": "0x560",
				"TYPE": "Text",
				"STRING": [
					"【ファル】",
					"「そんなこと言って、休みたいだけなんでしょ」"
				]
			},
			{
				"LABEL": "0x572",
				"TYPE": "KeyWait"
			},
			{
				"LABEL": "0x574",
				"TYPE": "NewPage"
			},
			{
				"LABEL": "0x576",
				"TYPE": "Text",
				"STRING": [
					"【クリス】",
					"「違うよ。ぱっと見てわかるくらいに、疲れてそうだっ",
					"　たから」"
				]
			},
			{
				"LABEL": "0x592",
				"TYPE": "KeyWait"
			},
			{
				"LABEL": "0x594",
				"TYPE": "MoveChar",
				"U32": [
					43,
					1,
					1
				]
			},
			{
				"LABEL": "0x5a8",
				"TYPE": "NewPage"
			},
			{
				"LABEL": "0x5aa",
				"TYPE": "Voice",
				"U32": [
					144008
				]
			},
			{
				"LABEL": "0x5b2",
				"TYPE": "Text",
				"STRING": [
					"【ファル】",
					"「……そっか。ありがと」"
				]
			},
			{
				"LABEL": "0x5c4",
				"TYPE": "KeyWait"
			},
			{
				"LABEL": "0x5c6",
				"TYPE": "NewPage"
			},
			{
				"LABEL": "0x5c8",
				"TYPE": "Text",
				"STRING": [
					"【クリス】",
					"「僕はどちらでも構わないから。決めて良いよ」"
				]
			},
			{
				"LABEL": "0x5da",
				"TYPE": "KeyWait"
			},
			{
				"LABEL": "0x5dc",
				"TYPE": "MoveChar",
				"U32": [
					45,
					1,
					1
				]
			},
			{
				"LABEL": "0x5f0",
				"TYPE": "NewPage"
			},
			{
				"LABEL": "0x5f2",
				"TYPE": "Voice",
				"U32": [
					144009
				]
			},
			{
				"LABEL": "0x5fa",
				"TYPE": "Text",
				"STRING": [
					"【ファル】",
					"「なら……」"
				]
			},
			{
				"LABEL": "0x60c",
				"TYPE": "KeyWait"
			},
			{
				"LABEL": "0x60e",
				"TYPE": "NewPage"
			},
			{
				"LABEL": "0x610",
				"TYPE": "Text",
				"STRING": [
					"自分の身体と相談するように、彼女は少しだけ難しそう",
					"な顔をして物思いに耽っている。"
				]
			},
			{
				"LABEL": "0x622",
				"TYPE": "KeyWait"
			},
			{
				"LABEL": "0x624",
				"TYPE": "NewPage"
			},
			{
				"LABEL": "0x626",
				"TYPE": "Text",
				"STRING": [
					"そしてしばらくすると、すっきりした顔で予想通りの答",
					"えを返した。"
				]
			},
			{
				"LABEL": "0x638",
				"TYPE": "KeyWait"
			},
			{
				"LABEL": "0x63a",
				"TYPE": "MoveChar",
				"U32": [
					40,
					1,
					1
				]
			},
			{
				"LABEL": "0x64e",
				"TYPE": "NewPage"
			},
			{
				"LABEL": "0x650",
				"TYPE": "Voice",
				"U32": [
					144010
				]
			},
			{
				"LABEL": "0x658",
				"TYPE": "Text",
				"STRING": [
					"【ファル】",
					"「練習しましょうか」"
				]
			},
			{
				"LABEL": "0x66a",
				"TYPE": "KeyWait"
			},
			{
				"LABEL": "0x66c",
				"TYPE": "NewPage"
			},
			{
				"LABEL": "0x66e",
				"TYPE": "Text",
				"STRING": [
					"【クリス】",
					"「……はい、そう言うと思ったよ」"
				]
			},
			{
				"LABEL": "0x680",
				"TYPE": "KeyWait"
			},
			{
				"LABEL": "0x682",
				"TYPE": "NewPage"
			},
			{
				"LABEL": "0x684",
				"TYPE": "Voice",
				"U32": [
					144011
				]
			},
			{
				"LABEL": "0x68c",
				"TYPE": "Text",
				"STRING": [
					"【ファル】",
					"「フォルテールは？」"
				]
			},
			{
				"LABEL": "0x69e",
				"TYPE": "KeyWait"
			},
			{
				"LABEL": "0x6a0",
				"TYPE": "NewPage"
			},
			{
				"LABEL": "0x6a2",
				"TYPE": "Text",
				"STRING": [
					"【クリス】",
					"「大丈夫」"
				]
			},
			{
				"LABEL": "0x6b4",
				"TYPE": "KeyWait"
			},
			{
				"LABEL": "0x6b6",
				"TYPE": "NewPage"
			},
			{
				"LABEL": "0x6b8",
				"TYPE": "Text",
				"STRING": [
					"足下に置いてあるフォルテールを指さす。"
				]
			},
			{
				"LABEL": "0x6c0",
				"TYPE": "KeyWait"
			},
			{
				"LABEL": "0x6c2",
				"TYPE": "MoveChar",
				"U32": [
					47,
					1,
					1
				]
			},
			{
				"LABEL": "0x6d6",
				"TYPE": "NewPage"
			},
			{
				"LABEL": "0x6d8",
				"TYPE": "Voice",
				"U32": [
					144012
				]
			},
			{
				"LABEL": "0x6e0",
				"TYPE": "Text",
				"STRING": [
					"【ファル】",
					"「よろしい。"
				]
			},
			{
				"LABEL": "0x6f2",
				"TYPE": "Wait",
				"U32": [
					500
				]
			},
			{
				"LABEL": "0x6fa",
				"TYPE": "MoveChar",
				"U32": [
					42,
					1,
					1
				]
			},
			{
				"LABEL": "0x70e",
				"TYPE": "Text",
				"STRING": [
					"じゃあ、学院に行く？　それとも別な場所",
					"　で？」"
				]
			},
			{
				"LABEL": "0x720",
				"TYPE": "KeyWait"
			},
			{
				"LABEL": "0x722",
				"TYPE": "NewPage"
			},
			{
				"LABEL": "0x724",
				"TYPE": "Text",
				"STRING": [
					"【クリス】",
					"「休みの日に学院は、ちょっとね」"
				]
			},
			{
				"LABEL": "0x736",
				"TYPE": "KeyWait"
			},
			{
				"LABEL": "0x738",
				"TYPE": "MoveChar",
				"U32": [
					40,
					1,
					1
				]
			},
			{
				"LABEL": "0x74c",
				"TYPE": "NewPage"
			},
			{
				"LABEL": "0x74e",
				"TYPE": "Voice",
				"U32": [
					144013
				]
			},
			{
				"LABEL": "0x756",
				"TYPE": "Text",
				"STRING": [
					"【ファル】",
					"「でも、クリスさんの家なら、わざわざ持ってくる必要",
					"　もなかったんじゃない？　"
				]
			},
			{
				"LABEL": "0x772",
				"TYPE": "Wait",
				"U32": [
					3000
				]
			},
			{
				"LABEL": "0x77a",
				"TYPE": "MoveChar",
				"U32": [
					45,
					1,
					1
				]
			},
			{
				"LABEL": "0x78e",
				"TYPE": "Text",
				"STRING": [
					"……ということは、私の家",
					"　くらいしかないか」"
				]
			},
			{
				"LABEL": "0x7a0",
				"TYPE": "KeyWait"
			},
			{
				"LABEL": "0x7a2",
				"TYPE": "NewPage"
			},
			{
				"LABEL": "0x7a4",
				"TYPE": "Text",
				"STRING": [
					"持ってくるように言ったのは、確かファルさんだったよ",
					"うな気もする。"
				]
			},
			{
				"LABEL": "0x7b6",
				"TYPE": "KeyWait"
			},
			{
				"LABEL": "0x7b8",
				"TYPE": "NewPage"
			},
			{
				"LABEL": "0x7ba",
				"TYPE": "Text",
				"STRING": [
					"そして、僕が学院に行きたがらないのも、ひょっとした",
					"ら予想していたんじゃないだろうか。"
				]
			},
			{
				"LABEL": "0x7cc",
				"TYPE": "KeyWait"
			},
			{
				"LABEL": "0x7ce",
				"TYPE": "NewPage"
			},
			{
				"LABEL": "0x7d0",
				"TYPE": "Text",
				"STRING": [
					"そんなことを、ふと考えてしまった。"
				]
			},
			{
				"LABEL": "0x7d8",
				"TYPE": "KeyWait"
			},
			{
				"LABEL": "0x7da",
				"TYPE": "NewPage"
			},
			{
				"LABEL": "0x7dc",
				"TYPE": "Text",
				"STRING": [
					"【クリス】",
					"「……そういうことになるね」"
				]
			},
			{
				"LABEL": "0x7ee",
				"TYPE": "KeyWait"
			},
			{
				"LABEL": "0x7f0",
				"TYPE": "MoveChar",
				"U32": [
					40,
					1,
					1
				]
			},
			{
				"LABEL": "0x804",
				"TYPE": "NewPage"
			},
			{
				"LABEL": "0x806",
				"TYPE": "Voice",
				"U32": [
					144014
				]
			},
			{
				"LABEL": "0x80e",
				"TYPE": "Text",
				"STRING": [
					"【ファル】",
					"「じゃ、行こうか」"
				]
			},
			{
				"LABEL": "0x820",
				"TYPE": "KeyWait"
			},
			{
				"LABEL": "0x822",
				"TYPE": "NewPage"
			},
			{
				"LABEL": "0x824",
				"TYPE": "Text",
				"STRING": [
					"でもファルさんは、にこやかな顔を崩そうとせずに、歩",
					"いていく。"
				]
			},
			{
				"LABEL": "0x836",
				"TYPE": "KeyWait"
			},
			{
				"LABEL": "0x838",
				"TYPE": "AllHideChar"
			},
			{
				"LABEL": "0x83a",
				"TYPE": "BGMStop"
			},
			{
				"LABEL": "0x83c",
				"TYPE": "TextHide"
			},
			{
				"LABEL": "0x83e",
				"TYPE": "BlackOut",
				"U32": [
					1
				]
			},
			{
				"LABEL": "0x846",
				"TYPE": "Wait",
				"U32": [
					1500
				]
			},
			{
				"LABEL": "0x84e",
				"TYPE": "AddMin",
				"U32": [
					20
				]
			},
			{
				"LABEL": "0x856",
				"TYPE": "SEPlay",
				"U32": [
					35
				]
			},
			{
				"LABEL": "0x85e",
				"TYPE": "FadeBGtoSetBG",
				"U32": [
					1300,
					1
				]
			},
			{
				"LABEL": "0x86c",
				"TYPE": "Wait",
				"U32": [
					1500
				]
			},
			{
				"LABEL": "0x874",
				"TYPE": "NewPage"
			},
			{
				"LABEL": "0x876",
				"TYPE": "Text",
				"STRING": [
					"【クリス】",
					"「失礼します」"
				]
			},
			{
				"LABEL": "0x888",
				"TYPE": "KeyWait"
			},
			{
				"LABEL": "0x88a",
				"TYPE": "NewPage"
			},
			{
				"LABEL": "0x88c",
				"TYPE": "Text",
				"STRING": [
					"そう声をかけ、ファルさんに続いて部屋に入ると、玄関",
					"にはこの前と同じように、二組のタオルが置いてあった。"
				]
			},
			{
				"LABEL": "0x89e",
				"TYPE": "KeyWait"
			},
			{
				"LABEL": "0x8a0",
				"TYPE": "MoveChar",
				"U32": [
					40,
					1,
					2
				]
			},
			{
				"LABEL": "0x8b4",
				"TYPE": "BGMPlay",
				"U32": [
					5
				]
			},
			{
				"LABEL": "0x8bc",
				"TYPE": "NewPage"
			},
			{
				"LABEL": "0x8be",
				"TYPE": "Voice",
				"U32": [
					144015
				]
			},
			{
				"LABEL": "0x8c6",
				"TYPE": "Text",
				"STRING": [
					"【ファル】",
					"「どうぞ。用意が良いでしょ」"
				]
			},
			{
				"LABEL": "0x8d8",
				"TYPE": "KeyWait"
			},
			{
				"LABEL": "0x8da",
				"TYPE": "NewPage"
			},
			{
				"LABEL": "0x8dc",
				"TYPE": "Text",
				"STRING": [
					"【クリス】",
					"「……最初からここに来るつもりだった？」"
				]
			},
			{
				"LABEL": "0x8ee",
				"TYPE": "KeyWait"
			},
			{
				"LABEL": "0x8f0",
				"TYPE": "MoveChar",
				"U32": [
					42,
					1,
					1
				]
			},
			{
				"LABEL": "0x904",
				"TYPE": "NewPage"
			},
			{
				"LABEL": "0x906",
				"TYPE": "Voice",
				"U32": [
					144016
				]
			},
			{
				"LABEL": "0x90e",
				"TYPE": "Text",
				"STRING": [
					"【ファル】",
					"「そうでもないよ。無駄にならなくて良かったってだけ」"
				]
			},
			{
				"LABEL": "0x920",
				"TYPE": "KeyWait"
			},
			{
				"LABEL": "0x922",
				"TYPE": "NewPage"
			},
			{
				"LABEL": "0x924",
				"TYPE": "Text",
				"STRING": [
					"良い香りのするタオルで髪と服を拭いていると、ファル",
					"さんはすでに部屋の奥へ入っていき、自分の持っていた",
					"鞄から見覚えのある楽譜を取り出していた。"
				]
			},
			{
				"LABEL": "0x940",
				"TYPE": "KeyWait"
			},
			{
				"LABEL": "0x942",
				"TYPE": "NewPage"
			},
			{
				"LABEL": "0x944",
				"TYPE": "Text",
				"STRING": [
					"【クリス】",
					"「それ、持って帰ってたの？」"
				]
			},
			{
				"LABEL": "0x956",
				"TYPE": "KeyWait"
			},
			{
				"LABEL": "0x958",
				"TYPE": "NewPage"
			},
			{
				"LABEL": "0x95a",
				"TYPE": "Text",
				"STRING": [
					"使い終わったタオルを畳んで机の上に置く。"
				]
			},
			{
				"LABEL": "0x962",
				"TYPE": "KeyWait"
			},
			{
				"LABEL": "0x964",
				"TYPE": "MoveChar",
				"U32": [
					40,
					1,
					1
				]
			},
			{
				"LABEL": "0x978",
				"TYPE": "NewPage"
			},
			{
				"LABEL": "0x97a",
				"TYPE": "Voice",
				"U32": [
					144017
				]
			},
			{
				"LABEL": "0x982",
				"TYPE": "Text",
				"STRING": [
					"【ファル】",
					"「イメージを忘れないためにね。とはいっても、全部頭",
					"　の中に入っているから、見なくても思い出せるんだけ",
					"　ど……」"
				]
			},
			{
				"LABEL": "0x9a8",
				"TYPE": "KeyWait"
			},
			{
				"LABEL": "0x9aa",
				"TYPE": "NewPage"
			},
			{
				"LABEL": "0x9ac",
				"TYPE": "Text",
				"STRING": [
					"【クリス】",
					"「ん？」"
				]
			},
			{
				"LABEL": "0x9be",
				"TYPE": "KeyWait"
			},
			{
				"LABEL": "0x9c0",
				"TYPE": "MoveChar",
				"U32": [
					43,
					1,
					1
				]
			},
			{
				"LABEL": "0x9d4",
				"TYPE": "NewPage"
			},
			{
				"LABEL": "0x9d6",
				"TYPE": "Voice",
				"U32": [
					144018
				]
			},
			{
				"LABEL": "0x9de",
				"TYPE": "Text",
				"STRING": [
					"【ファル】",
					"「なんとなく、自分が使い込んだ物だからかな？　持っ",
					"　てると安心する気がして」"
				]
			},
			{
				"LABEL": "0x9fa",
				"TYPE": "KeyWait"
			},
			{
				"LABEL": "0x9fc",
				"TYPE": "NewPage"
			},
			{
				"LABEL": "0x9fe",
				"TYPE": "Text",
				"STRING": [
					"数多くの書き込みのおかげで、初めての人なら見づらく",
					"て仕方がないような、汚れた楽譜。"
				]
			},
			{
				"LABEL": "0xa10",
				"TYPE": "KeyWait"
			},
			{
				"LABEL": "0xa12",
				"TYPE": "NewPage"
			},
			{
				"LABEL": "0xa14",
				"TYPE": "Text",
				"STRING": [
					"でも、ファルさんのように練習に練習を重ね、書き込ま",
					"れたことを自分のものとした彼女にとって、それはパー",
					"トナーとも呼べる大切な存在だった。"
				]
			},
			{
				"LABEL": "0xa30",
				"TYPE": "KeyWait"
			},
			{
				"LABEL": "0xa32",
				"TYPE": "NewPage"
			},
			{
				"LABEL": "0xa34",
				"TYPE": "Text",
				"STRING": [
					"だからファルさんがそれを持って安心するというのも、",
					"ごく自然なことだ。"
				]
			},
			{
				"LABEL": "0xa46",
				"TYPE": "KeyWait"
			},
			{
				"LABEL": "0xa48",
				"TYPE": "NewPage"
			},
			{
				"LABEL": "0xa4a",
				"TYPE": "Text",
				"STRING": [
					"【クリス】",
					"「よくわかるよ」"
				]
			},
			{
				"LABEL": "0xa5c",
				"TYPE": "KeyWait"
			},
			{
				"LABEL": "0xa5e",
				"TYPE": "MoveChar",
				"U32": [
					41,
					1,
					1
				]
			},
			{
				"LABEL": "0xa72",
				"TYPE": "NewPage"
			},
			{
				"LABEL": "0xa74",
				"TYPE": "Voice",
				"U32": [
					144019
				]
			},
			{
				"LABEL": "0xa7c",
				"TYPE": "Text",
				"STRING": [
					"【ファル】",
					"「ふふ」"
				]
			},
			{
				"LABEL": "0xa8e",
				"TYPE": "KeyWait"
			},
			{
				"LABEL": "0xa90",
				"TYPE": "NewPage"
			},
			{
				"LABEL": "0xa92",
				"TYPE": "Text",
				"STRING": [
					"【クリス】",
					"「……で、それを出したってことは？」"
				]
			},
			{
				"LABEL": "0xaa4",
				"TYPE": "KeyWait"
			},
			{
				"LABEL": "0xaa6",
				"TYPE": "NewPage"
			},
			{
				"LABEL": "0xaa8",
				"TYPE": "Voice",
				"U32": [
					144020
				]
			},
			{
				"LABEL": "0xab0",
				"TYPE": "Text",
				"STRING": [
					"【ファル】",
					"「用意は良い？」"
				]
			},
			{
				"LABEL": "0xac2",
				"TYPE": "KeyWait"
			},
			{
				"LABEL": "0xac4",
				"TYPE": "NewPage"
			},
			{
				"LABEL": "0xac6",
				"TYPE": "Text",
				"STRING": [
					"【クリス】",
					"「……急いでやらせていただきます」"
				]
			},
			{
				"LABEL": "0xad8",
				"TYPE": "KeyWait"
			},
			{
				"LABEL": "0xada",
				"TYPE": "MoveChar",
				"U32": [
					47,
					1,
					1
				]
			},
			{
				"LABEL": "0xaee",
				"TYPE": "NewPage"
			},
			{
				"LABEL": "0xaf0",
				"TYPE": "Voice",
				"U32": [
					144021
				]
			},
			{
				"LABEL": "0xaf8",
				"TYPE": "Text",
				"STRING": [
					"【ファル】",
					"「よろしい」"
				]
			},
			{
				"LABEL": "0xb0a",
				"TYPE": "KeyWait"
			},
			{
				"LABEL": "0xb0c",
				"TYPE": "AllHideChar"
			},
			{
				"LABEL": "0xb0e",
				"TYPE": "TextHide"
			},
			{
				"LABEL": "0xb10",
				"TYPE": "BGMStop"
			},
			{
				"LABEL": "0xb12",
				"TYPE": "Wait",
				"U32": [
					1000
				]
			},
			{
				"LABEL": "0xb1a",
				"TYPE": "NovelMode",
				"U32": [
					1
				]
			},
			{
				"LABEL": "0xb22",
				"TYPE": "Wait",
				"U32": [
					500
				]
			},
			{
				"LABEL": "0xb2a",
				"TYPE": "BGMPlay",
				"U32": [
					20
				]
			},
			{
				"LABEL": "0xb32",
				"TYPE": "NewPage"
			},
			{
				"LABEL": "0xb34",
				"TYPE": "Text",
				"STRING": [
					"彼女の声が、一層の艶やかさを増しているように聞こえ",
					"た。"
				]
			},
			{
				"LABEL": "0xb46",
				"TYPE": "KeyWait"
			},
			{
				"LABEL": "0xb48",
				"TYPE": "NewLine"
			},
			{
				"LABEL": "0xb4a",
				"TYPE": "Text",
				"STRING": [
					"帰ってからも毎日練習をかかさなかったことは、聞いた",
					"だけでもわかる。"
				]
			},
			{
				"LABEL": "0xb5c",
				"TYPE": "KeyWait"
			},
			{
				"LABEL": "0xb5e",
				"TYPE": "NewLine"
			},
			{
				"LABEL": "0xb60",
				"TYPE": "Text",
				"STRING": [
					"もちろん、聞かなくても、彼女を良く知る人だったら、",
					"疑うことすらしないだろう。"
				]
			},
			{
				"LABEL": "0xb72",
				"TYPE": "KeyWait"
			},
			{
				"LABEL": "0xb74",
				"TYPE": "NewLine"
			},
			{
				"LABEL": "0xb76",
				"TYPE": "NewLine"
			},
			{
				"LABEL": "0xb78",
				"TYPE": "Text",
				"STRING": [
					"一方、僕の方も毎日フォルテールに触れていたから、腕",
					"が鈍るようなこともなかった。"
				]
			},
			{
				"LABEL": "0xb8a",
				"TYPE": "KeyWait"
			},
			{
				"LABEL": "0xb8c",
				"TYPE": "NewLine"
			},
			{
				"LABEL": "0xb8e",
				"TYPE": "Text",
				"STRING": [
					"しかも他の誰でもない、フォーニとの練習だ。"
				]
			},
			{
				"LABEL": "0xb96",
				"TYPE": "KeyWait"
			},
			{
				"LABEL": "0xb98",
				"TYPE": "NewLine"
			},
			{
				"LABEL": "0xb9a",
				"TYPE": "NewLine"
			},
			{
				"LABEL": "0xb9c",
				"TYPE": "Text",
				"STRING": [
					"一週間以上の空白も、今の二人にはほとんど関係なかっ",
					"た。"
				]
			},
			{
				"LABEL": "0xbae",
				"TYPE": "KeyWait"
			},
			{
				"LABEL": "0xbb0",
				"TYPE": "NewLine"
			},
			{
				"LABEL": "0xbb2",
				"TYPE": "Text",
				"STRING": [
					"そして、フォーニの歌声にいつもよりも多く触れていた",
					"おかげでわかったことがある。"
				]
			},
			{
				"LABEL": "0xbc4",
				"TYPE": "KeyWait"
			},
			{
				"LABEL": "0xbc6",
				"TYPE": "NewPage"
			},
			{
				"LABEL": "0xbc8",
				"TYPE": "Text",
				"STRING": [
					"ファルさんの歌声に、今までになかった『なにか』を感",
					"じることができた。"
				]
			},
			{
				"LABEL": "0xbda",
				"TYPE": "KeyWait"
			},
			{
				"LABEL": "0xbdc",
				"TYPE": "NewLine"
			},
			{
				"LABEL": "0xbde",
				"TYPE": "Text",
				"STRING": [
					"フォーニと、そして彼女自身も足りないと言っていたな",
					"にかが、そこにあると僕は感じていた。"
				]
			},
			{
				"LABEL": "0xbf0",
				"TYPE": "KeyWait"
			},
			{
				"LABEL": "0xbf2",
				"TYPE": "NewLine"
			},
			{
				"LABEL": "0xbf4",
				"TYPE": "NewLine"
			},
			{
				"LABEL": "0xbf6",
				"TYPE": "Text",
				"STRING": [
					"まるでフォーニと歌っている時のように、淀みない音と",
					"空気の流れを肌で感じる。"
				]
			},
			{
				"LABEL": "0xc08",
				"TYPE": "KeyWait"
			},
			{
				"LABEL": "0xc0a",
				"TYPE": "NewLine"
			},
			{
				"LABEL": "0xc0c",
				"TYPE": "NewLine"
			},
			{
				"LABEL": "0xc0e",
				"TYPE": "Text",
				"STRING": [
					"僕達が会っていなかった期間に、なにかがあったんだろ",
					"うか？"
				]
			},
			{
				"LABEL": "0xc20",
				"TYPE": "KeyWait"
			},
			{
				"LABEL": "0xc22",
				"TYPE": "NewLine"
			},
			{
				"LABEL": "0xc24",
				"TYPE": "Text",
				"STRING": [
					"それとも、時が自然に解決してくれるようななにかであ",
					"ったのか。"
				]
			},
			{
				"LABEL": "0xc36",
				"TYPE": "KeyWait"
			},
			{
				"LABEL": "0xc38",
				"TYPE": "NewLine"
			},
			{
				"LABEL": "0xc3a",
				"TYPE": "NewLine"
			},
			{
				"LABEL": "0xc3c",
				"TYPE": "Text",
				"STRING": [
					"無意識の内にフォルテールを弾き、僕はそんなことを考",
					"えていた。"
				]
			},
			{
				"LABEL": "0xc4e",
				"TYPE": "KeyWait"
			},
			{
				"LABEL": "0xc50",
				"TYPE": "TextHide"
			},
			{
				"LABEL": "0xc52",
				"TYPE": "BGMStop"
			},
			{
				"LABEL": "0xc54",
				"TYPE": "BlackOut",
				"U32": [
					18
				]
			},
			{
				"LABEL": "0xc5c",
				"TYPE": "Wait",
				"U32": [
					500
				]
			},
			{
				"LABEL": "0xc64",
				"TYPE": "AddMin",
				"U32": [
					5
				]
			},
			{
				"LABEL": "0xc6c",
				"TYPE": "NovelMode",
				"U32": [
					0
				]
			},
			{
				"LABEL": "0xc74",
				"TYPE": "FadeBGtoSetBG",
				"U32": [
					1300,
					18
				]
			},
			{
				"LABEL": "0xc82",
				"TYPE": "Wait",
				"U32": [
					1000
				]
			},
			{
				"LABEL": "0xc8a",
				"TYPE": "MoveChar",
				"U32": [
					45,
					1,
					2
				]
			},
			{
				"LABEL": "0xc9e",
				"TYPE": "BGMPlay",
				"U32": [
					5
				]
			},
			{
				"LABEL": "0xca6",
				"TYPE": "NewPage"
			},
			{
				"LABEL": "0xca8",
				"TYPE": "Voice",
				"U32": [
					144022
				]
			},
			{
				"LABEL": "0xcb0",
				"TYPE": "Text",
				"STRING": [
					"【ファル】",
					"「……ふう」"
				]
			},
			{
				"LABEL": "0xcc2",
				"TYPE": "KeyWait"
			},
			{
				"LABEL": "0xcc4",
				"TYPE": "NewPage"
			},
			{
				"LABEL": "0xcc6",
				"TYPE": "Text",
				"STRING": [
					"一曲を歌い終えたところで、ファルさんは疲れを吐き出",
					"すように大きく呼吸した。"
				]
			},
			{
				"LABEL": "0xcd8",
				"TYPE": "KeyWait"
			},
			{
				"LABEL": "0xcda",
				"TYPE": "NewPage"
			},
			{
				"LABEL": "0xcdc",
				"TYPE": "Text",
				"STRING": [
					"【クリス】",
					"「大丈夫？」"
				]
			},
			{
				"LABEL": "0xcee",
				"TYPE": "KeyWait"
			},
			{
				"LABEL": "0xcf0",
				"TYPE": "MoveChar",
				"U32": [
					44,
					1,
					1
				]
			},
			{
				"LABEL": "0xd04",
				"TYPE": "NewPage"
			},
			{
				"LABEL": "0xd06",
				"TYPE": "Voice",
				"U32": [
					144023
				]
			},
			{
				"LABEL": "0xd0e",
				"TYPE": "Text",
				"STRING": [
					"【ファル】",
					"「あ、うん。やっぱりちょっと疲れてたみたい」"
				]
			},
			{
				"LABEL": "0xd20",
				"TYPE": "KeyWait"
			},
			{
				"LABEL": "0xd22",
				"TYPE": "NewPage"
			},
			{
				"LABEL": "0xd24",
				"TYPE": "Text",
				"STRING": [
					"もう無理をするのをやめたのか、彼女は近くの椅子に腰",
					"掛けてからもう一度深呼吸をする。"
				]
			},
			{
				"LABEL": "0xd36",
				"TYPE": "KeyWait"
			},
			{
				"LABEL": "0xd38",
				"TYPE": "NewPage"
			},
			{
				"LABEL": "0xd3a",
				"TYPE": "Text",
				"STRING": [
					"彼女自身が大丈夫だと言うものの、体調があまり良くな",
					"いのは一目でわかった。"
				]
			},
			{
				"LABEL": "0xd4c",
				"TYPE": "KeyWait"
			},
			{
				"LABEL": "0xd4e",
				"TYPE": "NewPage"
			},
			{
				"LABEL": "0xd50",
				"TYPE": "Text",
				"STRING": [
					"再びなにか言葉をかけようかと迷っていると、それより",
					"も先にファルさんが質問した。"
				]
			},
			{
				"LABEL": "0xd62",
				"TYPE": "KeyWait"
			},
			{
				"LABEL": "0xd64",
				"TYPE": "MoveChar",
				"U32": [
					44,
					1,
					1
				]
			},
			{
				"LABEL": "0xd78",
				"TYPE": "NewPage"
			},
			{
				"LABEL": "0xd7a",
				"TYPE": "Voice",
				"U32": [
					144024
				]
			},
			{
				"LABEL": "0xd82",
				"TYPE": "Text",
				"STRING": [
					"【ファル】",
					"「ねえ、今日の歌はどうだった？」"
				]
			},
			{
				"LABEL": "0xd94",
				"TYPE": "KeyWait"
			},
			{
				"LABEL": "0xd96",
				"TYPE": "NewPage"
			},
			{
				"LABEL": "0xd98",
				"TYPE": "Text",
				"STRING": [
					"【クリス】",
					"「……それは、言わなくてもわかることじゃない？」"
				]
			},
			{
				"LABEL": "0xdaa",
				"TYPE": "KeyWait"
			},
			{
				"LABEL": "0xdac",
				"TYPE": "NewPage"
			},
			{
				"LABEL": "0xdae",
				"TYPE": "Text",
				"STRING": [
					"一言で言い表すのなら、素晴らしい、ということになる",
					"んだろうけど……。"
				]
			},
			{
				"LABEL": "0xdc0",
				"TYPE": "KeyWait"
			},
			{
				"LABEL": "0xdc2",
				"TYPE": "NewPage"
			},
			{
				"LABEL": "0xdc4",
				"TYPE": "Text",
				"STRING": [
					"自分たちでそれを言ってしまったら、嘘っぽくなる。"
				]
			},
			{
				"LABEL": "0xdcc",
				"TYPE": "KeyWait"
			},
			{
				"LABEL": "0xdce",
				"TYPE": "NewPage"
			},
			{
				"LABEL": "0xdd0",
				"TYPE": "Text",
				"STRING": [
					"それに、正しい評価を下せるのは、最後にはそれを聴く",
					"者だけだった。"
				]
			},
			{
				"LABEL": "0xde2",
				"TYPE": "KeyWait"
			},
			{
				"LABEL": "0xde4",
				"TYPE": "NewPage"
			},
			{
				"LABEL": "0xde6",
				"TYPE": "Voice",
				"U32": [
					144025
				]
			},
			{
				"LABEL": "0xdee",
				"TYPE": "Text",
				"STRING": [
					"【ファル】",
					"「クリスさんは、聴いててどう思った？」"
				]
			},
			{
				"LABEL": "0xe00",
				"TYPE": "KeyWait"
			},
			{
				"LABEL": "0xe02",
				"TYPE": "NewPage"
			},
			{
				"LABEL": "0xe04",
				"TYPE": "Text",
				"STRING": [
					"【クリス】",
					"「正直に言っても、お世辞だと思わないでくれる？」"
				]
			},
			{
				"LABEL": "0xe16",
				"TYPE": "KeyWait"
			},
			{
				"LABEL": "0xe18",
				"TYPE": "MoveChar",
				"U32": [
					40,
					1,
					1
				]
			},
			{
				"LABEL": "0xe2c",
				"TYPE": "NewPage"
			},
			{
				"LABEL": "0xe2e",
				"TYPE": "Voice",
				"U32": [
					144026
				]
			},
			{
				"LABEL": "0xe36",
				"TYPE": "Text",
				"STRING": [
					"【ファル】",
					"「……その言い方が、すでにお世辞みたいね」"
				]
			},
			{
				"LABEL": "0xe48",
				"TYPE": "KeyWait"
			},
			{
				"LABEL": "0xe4a",
				"TYPE": "NewPage"
			},
			{
				"LABEL": "0xe4c",
				"TYPE": "Text",
				"STRING": [
					"【クリス】",
					"「良かったと思う」"
				]
			},
			{
				"LABEL": "0xe5e",
				"TYPE": "KeyWait"
			},
			{
				"LABEL": "0xe60",
				"TYPE": "MoveChar",
				"U32": [
					45,
					1,
					1
				]
			},
			{
				"LABEL": "0xe74",
				"TYPE": "NewPage"
			},
			{
				"LABEL": "0xe76",
				"TYPE": "Text",
				"STRING": [
					"真面目にそう答えるとファルさんは笑うのを止め、真剣",
					"に、聞き入るように僕の次の言葉を待った。"
				]
			},
			{
				"LABEL": "0xe88",
				"TYPE": "KeyWait"
			},
			{
				"LABEL": "0xe8a",
				"TYPE": "NewPage"
			},
			{
				"LABEL": "0xe8c",
				"TYPE": "Text",
				"STRING": [
					"【クリス】",
					"「いつか、足りない物があるって言ってたよね」"
				]
			},
			{
				"LABEL": "0xe9e",
				"TYPE": "KeyWait"
			},
			{
				"LABEL": "0xea0",
				"TYPE": "NewPage"
			},
			{
				"LABEL": "0xea2",
				"TYPE": "Voice",
				"U32": [
					144027
				]
			},
			{
				"LABEL": "0xeaa",
				"TYPE": "Text",
				"STRING": [
					"【ファル】",
					"「……うん。クリスさんにも、感じられたんでしょ？」"
				]
			},
			{
				"LABEL": "0xebc",
				"TYPE": "KeyWait"
			},
			{
				"LABEL": "0xebe",
				"TYPE": "NewPage"
			},
			{
				"LABEL": "0xec0",
				"TYPE": "Text",
				"STRING": [
					"【クリス】",
					"「あの時は、確かにね……でも、それが今日は感じられ",
					"　なかったかな」"
				]
			},
			{
				"LABEL": "0xedc",
				"TYPE": "KeyWait"
			},
			{
				"LABEL": "0xede",
				"TYPE": "MoveChar",
				"U32": [
					42,
					1,
					1
				]
			},
			{
				"LABEL": "0xef2",
				"TYPE": "NewPage"
			},
			{
				"LABEL": "0xef4",
				"TYPE": "Voice",
				"U32": [
					144028
				]
			},
			{
				"LABEL": "0xefc",
				"TYPE": "Text",
				"STRING": [
					"【ファル】",
					"「……本当に？」"
				]
			},
			{
				"LABEL": "0xf0e",
				"TYPE": "KeyWait"
			},
			{
				"LABEL": "0xf10",
				"TYPE": "NewPage"
			},
			{
				"LABEL": "0xf12",
				"TYPE": "Text",
				"STRING": [
					"僕は黙って頷いた。"
				]
			},
			{
				"LABEL": "0xf1a",
				"TYPE": "KeyWait"
			},
			{
				"LABEL": "0xf1c",
				"TYPE": "NewPage"
			},
			{
				"LABEL": "0xf1e",
				"TYPE": "Text",
				"STRING": [
					"これ以上言葉を続け、飾りたてても、どんどん嘘のよう",
					"に聞こえてしまうだろう。"
				]
			},
			{
				"LABEL": "0xf30",
				"TYPE": "KeyWait"
			},
			{
				"LABEL": "0xf32",
				"TYPE": "NewPage"
			},
			{
				"LABEL": "0xf34",
				"TYPE": "Text",
				"STRING": [
					"だから僕は真剣に、媚びているわけでもなく、真実を口",
					"にしているのだと無言で告げた。"
				]
			},
			{
				"LABEL": "0xf46",
				"TYPE": "KeyWait"
			},
			{
				"LABEL": "0xf48",
				"TYPE": "MoveChar",
				"U32": [
					40,
					1,
					1
				]
			},
			{
				"LABEL": "0xf5c",
				"TYPE": "NewPage"
			},
			{
				"LABEL": "0xf5e",
				"TYPE": "Voice",
				"U32": [
					144029
				]
			},
			{
				"LABEL": "0xf66",
				"TYPE": "Text",
				"STRING": [
					"【ファル】",
					"「……そっか」"
				]
			},
			{
				"LABEL": "0xf78",
				"TYPE": "KeyWait"
			},
			{
				"LABEL": "0xf7a",
				"TYPE": "NewPage"
			},
			{
				"LABEL": "0xf7c",
				"TYPE": "Text",
				"STRING": [
					"今日はもう、これ以上の練習は逆効果かもしれない。"
				]
			},
			{
				"LABEL": "0xf84",
				"TYPE": "KeyWait"
			},
			{
				"LABEL": "0xf86",
				"TYPE": "NewPage"
			},
			{
				"LABEL": "0xf88",
				"TYPE": "Text",
				"STRING": [
					"そう感じた僕は、フォルテールを片づけ始める。"
				]
			},
			{
				"LABEL": "0xf90",
				"TYPE": "KeyWait"
			},
			{
				"LABEL": "0xf92",
				"TYPE": "MoveChar",
				"U32": [
					42,
					1,
					1
				]
			},
			{
				"LABEL": "0xfa6",
				"TYPE": "NewPage"
			},
			{
				"LABEL": "0xfa8",
				"TYPE": "Voice",
				"U32": [
					144030
				]
			},
			{
				"LABEL": "0xfb0",
				"TYPE": "Text",
				"STRING": [
					"【ファル】",
					"「あ」"
				]
			},
			{
				"LABEL": "0xfc2",
				"TYPE": "KeyWait"
			},
			{
				"LABEL": "0xfc4",
				"TYPE": "NewPage"
			},
			{
				"LABEL": "0xfc6",
				"TYPE": "Text",
				"STRING": [
					"【クリス】",
					"「練習はまた明日から」"
				]
			},
			{
				"LABEL": "0xfd8",
				"TYPE": "KeyWait"
			},
			{
				"LABEL": "0xfda",
				"TYPE": "MoveChar",
				"U32": [
					40,
					1,
					1
				]
			},
			{
				"LABEL": "0xfee",
				"TYPE": "NewPage"
			},
			{
				"LABEL": "0xff0",
				"TYPE": "Voice",
				"U32": [
					144031
				]
			},
			{
				"LABEL": "0xff8",
				"TYPE": "Text",
				"STRING": [
					"【ファル】",
					"「……うん、そうだね」"
				]
			},
			{
				"LABEL": "0x100a",
				"TYPE": "KeyWait"
			},
			{
				"LABEL": "0x100c",
				"TYPE": "NewPage"
			},
			{
				"LABEL": "0x100e",
				"TYPE": "Text",
				"STRING": [
					"【クリス】",
					"「これは最初に言っておかなくちゃいけないけど、けし",
					"　て自分が休みたいから言ってるわけじゃないんだから",
					"　ね」"
				]
			},
			{
				"LABEL": "0x1034",
				"TYPE": "KeyWait"
			},
			{
				"LABEL": "0x1036",
				"TYPE": "MoveChar",
				"U32": [
					43,
					1,
					1
				]
			},
			{
				"LABEL": "0x104a",
				"TYPE": "NewPage"
			},
			{
				"LABEL": "0x104c",
				"TYPE": "Voice",
				"U32": [
					144032
				]
			},
			{
				"LABEL": "0x1054",
				"TYPE": "Text",
				"STRING": [
					"【ファル】",
					"「……ありがと」"
				]
			},
			{
				"LABEL": "0x1066",
				"TYPE": "KeyWait"
			},
			{
				"LABEL": "0x1068",
				"TYPE": "MoveChar",
				"U32": [
					40,
					1,
					1
				]
			},
			{
				"LABEL": "0x107c",
				"TYPE": "NewPage"
			},
			{
				"LABEL": "0x107e",
				"TYPE": "Text",
				"STRING": [
					"まだ来て間もなかったし、ファルさんがすぐに練習を始",
					"めてしまったから、帰る支度は驚くほど早く終わった。"
				]
			},
			{
				"LABEL": "0x1090",
				"TYPE": "KeyWait"
			},
			{
				"LABEL": "0x1092",
				"TYPE": "NewPage"
			},
			{
				"LABEL": "0x1094",
				"TYPE": "Text",
				"STRING": [
					"フォルテールを肩に担ぎ、まだ椅子で休んでいるファル",
					"さんに声をかける。"
				]
			},
			{
				"LABEL": "0x10a6",
				"TYPE": "KeyWait"
			},
			{
				"LABEL": "0x10a8",
				"TYPE": "NewPage"
			},
			{
				"LABEL": "0x10aa",
				"TYPE": "Text",
				"STRING": [
					"【クリス】",
					"「そういえばさ、なにかあったの？」"
				]
			},
			{
				"LABEL": "0x10bc",
				"TYPE": "KeyWait"
			},
			{
				"LABEL": "0x10be",
				"TYPE": "MoveChar",
				"U32": [
					42,
					1,
					1
				]
			},
			{
				"LABEL": "0x10d2",
				"TYPE": "NewPage"
			},
			{
				"LABEL": "0x10d4",
				"TYPE": "Text",
				"STRING": [
					"さりげなく聞いたつもりだったその質問に、ファルさん",
					"は座ったまま目を見開いた。"
				]
			},
			{
				"LABEL": "0x10e6",
				"TYPE": "KeyWait"
			},
			{
				"LABEL": "0x10e8",
				"TYPE": "MoveChar",
				"U32": [
					44,
					1,
					1
				]
			},
			{
				"LABEL": "0x10fc",
				"TYPE": "NewPage"
			},
			{
				"LABEL": "0x10fe",
				"TYPE": "Text",
				"STRING": [
					"それですぐに、なにかがあったのだとは分かったけど、",
					"それ以上の内容――つまり実際に何があったかまで分か",
					"らなかったし、聞けないとも思った。"
				]
			},
			{
				"LABEL": "0x111a",
				"TYPE": "KeyWait"
			},
			{
				"LABEL": "0x111c",
				"TYPE": "NewPage"
			},
			{
				"LABEL": "0x111e",
				"TYPE": "Text",
				"STRING": [
					"【クリス】",
					"「なければいいんだ。じゃ、今日はよく休んで、明日ま",
					"　た練習しよう」"
				]
			},
			{
				"LABEL": "0x113a",
				"TYPE": "KeyWait"
			},
			{
				"LABEL": "0x113c",
				"TYPE": "MoveChar",
				"U32": [
					40,
					1,
					1
				]
			},
			{
				"LABEL": "0x1150",
				"TYPE": "NewPage"
			},
			{
				"LABEL": "0x1152",
				"TYPE": "Voice",
				"U32": [
					144033
				]
			},
			{
				"LABEL": "0x115a",
				"TYPE": "Text",
				"STRING": [
					"【ファル】",
					"「うん。そこまで送るよ」"
				]
			},
			{
				"LABEL": "0x116c",
				"TYPE": "KeyWait"
			},
			{
				"LABEL": "0x116e",
				"TYPE": "NewPage"
			},
			{
				"LABEL": "0x1170",
				"TYPE": "Text",
				"STRING": [
					"【クリス】",
					"「あ、別にいいよ」"
				]
			},
			{
				"LABEL": "0x1182",
				"TYPE": "KeyWait"
			},
			{
				"LABEL": "0x1184",
				"TYPE": "NewPage"
			},
			{
				"LABEL": "0x1186",
				"TYPE": "Text",
				"STRING": [
					"と返事するまもなく、ファルさんは立ち上がってドアの",
					"前まで歩いた。"
				]
			},
			{
				"LABEL": "0x1198",
				"TYPE": "KeyWait"
			},
			{
				"LABEL": "0x119a",
				"TYPE": "NewPage"
			},
			{
				"LABEL": "0x119c",
				"TYPE": "Text",
				"STRING": [
					"その後ろに続き、彼女が開けるよりも先にそのドアに手",
					"をかける。"
				]
			},
			{
				"LABEL": "0x11ae",
				"TYPE": "KeyWait"
			},
			{
				"LABEL": "0x11b0",
				"TYPE": "NewPage"
			},
			{
				"LABEL": "0x11b2",
				"TYPE": "Text",
				"STRING": [
					"【クリス】",
					"「じゃあ、ここまでで。また明日からの練習だけど、ど",
					"　うする？」"
				]
			},
			{
				"LABEL": "0x11ce",
				"TYPE": "KeyWait"
			},
			{
				"LABEL": "0x11d0",
				"TYPE": "MoveChar",
				"U32": [
					42,
					1,
					1
				]
			},
			{
				"LABEL": "0x11e4",
				"TYPE": "NewPage"
			},
			{
				"LABEL": "0x11e6",
				"TYPE": "Voice",
				"U32": [
					144034
				]
			},
			{
				"LABEL": "0x11ee",
				"TYPE": "Text",
				"STRING": [
					"【ファル】",
					"「そうね……三年の個人レッスンは、新年に入ってから",
					"　はないから」"
				]
			},
			{
				"LABEL": "0x120a",
				"TYPE": "KeyWait"
			},
			{
				"LABEL": "0x120c",
				"TYPE": "NewPage"
			},
			{
				"LABEL": "0x120e",
				"TYPE": "Text",
				"STRING": [
					"【クリス】",
					"「……お昼から？」"
				]
			},
			{
				"LABEL": "0x1220",
				"TYPE": "KeyWait"
			},
			{
				"LABEL": "0x1222",
				"TYPE": "MoveChar",
				"U32": [
					40,
					1,
					1
				]
			},
			{
				"LABEL": "0x1236",
				"TYPE": "NewPage"
			},
			{
				"LABEL": "0x1238",
				"TYPE": "Voice",
				"U32": [
					144035
				]
			},
			{
				"LABEL": "0x1240",
				"TYPE": "Text",
				"STRING": [
					"【ファル】",
					"「朝から……というのはさすがにかわいそうだから、コ",
					"　ーデル先生の個人レッスンがあった時間からで良いよ」"
				]
			},
			{
				"LABEL": "0x125c",
				"TYPE": "KeyWait"
			},
			{
				"LABEL": "0x125e",
				"TYPE": "NewPage"
			},
			{
				"LABEL": "0x1260",
				"TYPE": "Text",
				"STRING": [
					"【クリス】",
					"「……十時か。それなら大丈夫かな」"
				]
			},
			{
				"LABEL": "0x1272",
				"TYPE": "KeyWait"
			},
			{
				"LABEL": "0x1274",
				"TYPE": "MoveChar",
				"U32": [
					47,
					1,
					1
				]
			},
			{
				"LABEL": "0x1288",
				"TYPE": "NewPage"
			},
			{
				"LABEL": "0x128a",
				"TYPE": "Voice",
				"U32": [
					144036
				]
			},
			{
				"LABEL": "0x1292",
				"TYPE": "Text",
				"STRING": [
					"【ファル】",
					"「遅れないように。"
				]
			},
			{
				"LABEL": "0x12a4",
				"TYPE": "Wait",
				"U32": [
					800
				]
			},
			{
				"LABEL": "0x12ac",
				"TYPE": "MoveChar",
				"U32": [
					42,
					1,
					1
				]
			},
			{
				"LABEL": "0x12c0",
				"TYPE": "Text",
				"STRING": [
					"それでさ、コーデル先生で思い出し",
					"　たんだけど」"
				]
			},
			{
				"LABEL": "0x12d2",
				"TYPE": "KeyWait"
			},
			{
				"LABEL": "0x12d4",
				"TYPE": "NewPage"
			},
			{
				"LABEL": "0x12d6",
				"TYPE": "Text",
				"STRING": [
					"【クリス】",
					"「そういえば、一回聴かせに来いって言ってたっけ」"
				]
			},
			{
				"LABEL": "0x12e8",
				"TYPE": "KeyWait"
			},
			{
				"LABEL": "0x12ea",
				"TYPE": "MoveChar",
				"U32": [
					40,
					1,
					1
				]
			},
			{
				"LABEL": "0x12fe",
				"TYPE": "NewPage"
			},
			{
				"LABEL": "0x1300",
				"TYPE": "Voice",
				"U32": [
					144037
				]
			},
			{
				"LABEL": "0x1308",
				"TYPE": "Text",
				"STRING": [
					"【ファル】",
					"「うん。明日にでも行ってみる？」"
				]
			},
			{
				"LABEL": "0x131a",
				"TYPE": "KeyWait"
			},
			{
				"LABEL": "0x131c",
				"TYPE": "NewPage"
			},
			{
				"LABEL": "0x131e",
				"TYPE": "Text",
				"STRING": [
					"【クリス】",
					"「うん……そうだね。なら、今日はよく休んでおくよう",
					"　に」"
				]
			},
			{
				"LABEL": "0x133a",
				"TYPE": "KeyWait"
			},
			{
				"LABEL": "0x133c",
				"TYPE": "MoveChar",
				"U32": [
					41,
					1,
					1
				]
			},
			{
				"LABEL": "0x1350",
				"TYPE": "NewPage"
			},
			{
				"LABEL": "0x1352",
				"TYPE": "Voice",
				"U32": [
					144038
				]
			},
			{
				"LABEL": "0x135a",
				"TYPE": "Text",
				"STRING": [
					"【ファル】",
					"「……はい」"
				]
			},
			{
				"LABEL": "0x136c",
				"TYPE": "KeyWait"
			},
			{
				"LABEL": "0x136e",
				"TYPE": "NewPage"
			},
			{
				"LABEL": "0x1370",
				"TYPE": "Text",
				"STRING": [
					"いつもとは立場が逆になっているけど、ファルさんは素",
					"直に頷いた。"
				]
			},
			{
				"LABEL": "0x1382",
				"TYPE": "KeyWait"
			},
			{
				"LABEL": "0x1384",
				"TYPE": "NewPage"
			},
			{
				"LABEL": "0x1386",
				"TYPE": "Text",
				"STRING": [
					"【クリス】",
					"「じゃ、また明日」"
				]
			},
			{
				"LABEL": "0x1398",
				"TYPE": "KeyWait"
			},
			{
				"LABEL": "0x139a",
				"TYPE": "MoveChar",
				"U32": [
					42,
					1,
					1
				]
			},
			{
				"LABEL": "0x13ae",
				"TYPE": "NewPage"
			},
			{
				"LABEL": "0x13b0",
				"TYPE": "Voice",
				"U32": [
					144039
				]
			},
			{
				"LABEL": "0x13b8",
				"TYPE": "Text",
				"STRING": [
					"【ファル】",
					"「……あ」"
				]
			},
			{
				"LABEL": "0x13ca",
				"TYPE": "KeyWait"
			},
			{
				"LABEL": "0x13cc",
				"TYPE": "NewPage"
			},
			{
				"LABEL": "0x13ce",
				"TYPE": "Text",
				"STRING": [
					"手をかけたままだったドアのノブを回そうとすると、な",
					"にか言いたそうにファルさんが小さな声を挙げた。"
				]
			},
			{
				"LABEL": "0x13e0",
				"TYPE": "KeyWait"
			},
			{
				"LABEL": "0x13e2",
				"TYPE": "NewPage"
			},
			{
				"LABEL": "0x13e4",
				"TYPE": "Text",
				"STRING": [
					"【クリス】",
					"「ん？」"
				]
			},
			{
				"LABEL": "0x13f6",
				"TYPE": "KeyWait"
			},
			{
				"LABEL": "0x13f8",
				"TYPE": "NewPage"
			},
			{
				"LABEL": "0x13fa",
				"TYPE": "Voice",
				"U32": [
					144040
				]
			},
			{
				"LABEL": "0x1402",
				"TYPE": "Text",
				"STRING": [
					"【ファル】",
					"「あのね……ひとつ、聞いていいかな」"
				]
			},
			{
				"LABEL": "0x1414",
				"TYPE": "KeyWait"
			},
			{
				"LABEL": "0x1416",
				"TYPE": "NewPage"
			},
			{
				"LABEL": "0x1418",
				"TYPE": "Text",
				"STRING": [
					"【クリス】",
					"「あ、ああ」"
				]
			},
			{
				"LABEL": "0x142a",
				"TYPE": "KeyWait"
			},
			{
				"LABEL": "0x142c",
				"TYPE": "MoveChar",
				"U32": [
					44,
					1,
					1
				]
			},
			{
				"LABEL": "0x1440",
				"TYPE": "NewPage"
			},
			{
				"LABEL": "0x1442",
				"TYPE": "Voice",
				"U32": [
					144041
				]
			},
			{
				"LABEL": "0x144a",
				"TYPE": "Text",
				"STRING": [
					"【ファル】",
					"「私の歌は……価値のあるものなのかな？」"
				]
			},
			{
				"LABEL": "0x145c",
				"TYPE": "KeyWait"
			},
			{
				"LABEL": "0x145e",
				"TYPE": "NewPage"
			},
			{
				"LABEL": "0x1460",
				"TYPE": "Text",
				"STRING": [
					"【クリス】",
					"「……価値？」"
				]
			},
			{
				"LABEL": "0x1472",
				"TYPE": "KeyWait"
			},
			{
				"LABEL": "0x1474",
				"TYPE": "NewPage"
			},
			{
				"LABEL": "0x1476",
				"TYPE": "Voice",
				"U32": [
					144042
				]
			},
			{
				"LABEL": "0x147e",
				"TYPE": "Text",
				"STRING": [
					"【ファル】",
					"「私は……プロになれるかな」"
				]
			},
			{
				"LABEL": "0x1490",
				"TYPE": "KeyWait"
			},
			{
				"LABEL": "0x1492",
				"TYPE": "NewPage"
			},
			{
				"LABEL": "0x1494",
				"TYPE": "Text",
				"STRING": [
					"一旦握ったドアノブから手を離し、正面から向かい合う。"
				]
			},
			{
				"LABEL": "0x149c",
				"TYPE": "KeyWait"
			},
			{
				"LABEL": "0x149e",
				"TYPE": "MoveChar",
				"U32": [
					44,
					1,
					1
				]
			},
			{
				"LABEL": "0x14b2",
				"TYPE": "NewPage"
			},
			{
				"LABEL": "0x14b4",
				"TYPE": "Text",
				"STRING": [
					"それに気づいたファルさんが、一瞬怒ったような顔をし",
					"て、それからうつむいた。"
				]
			},
			{
				"LABEL": "0x14c6",
				"TYPE": "KeyWait"
			},
			{
				"LABEL": "0x14c8",
				"TYPE": "NewPage"
			},
			{
				"LABEL": "0x14ca",
				"TYPE": "Text",
				"STRING": [
					"ただ、それは僕に対してではなく、自分に対して向けら",
					"れたもののようだった。"
				]
			},
			{
				"LABEL": "0x14dc",
				"TYPE": "KeyWait"
			},
			{
				"LABEL": "0x14de",
				"TYPE": "MoveChar",
				"U32": [
					40,
					1,
					1
				]
			},
			{
				"LABEL": "0x14f2",
				"TYPE": "NewPage"
			},
			{
				"LABEL": "0x14f4",
				"TYPE": "Voice",
				"U32": [
					144043
				]
			},
			{
				"LABEL": "0x14fc",
				"TYPE": "Text",
				"STRING": [
					"【ファル】",
					"「気にしないで」"
				]
			},
			{
				"LABEL": "0x150e",
				"TYPE": "KeyWait"
			},
			{
				"LABEL": "0x1510",
				"TYPE": "NewPage"
			},
			{
				"LABEL": "0x1512",
				"TYPE": "Text",
				"STRING": [
					"【クリス】",
					"「えっとさ……あんまり上手く言える自信がないから、",
					"　簡単に言うね」"
				]
			},
			{
				"LABEL": "0x152e",
				"TYPE": "KeyWait"
			},
			{
				"LABEL": "0x1530",
				"TYPE": "NewPage"
			},
			{
				"LABEL": "0x1532",
				"TYPE": "Text",
				"STRING": [
					"【ファル】",
					"「……」"
				]
			},
			{
				"LABEL": "0x1544",
				"TYPE": "KeyWait"
			},
			{
				"LABEL": "0x1546",
				"TYPE": "NewPage"
			},
			{
				"LABEL": "0x1548",
				"TYPE": "Text",
				"STRING": [
					"【クリス】",
					"「あるし、なれるよ。ファルさんにはその実力もあるし、",
					"　その資格もある」"
				]
			},
			{
				"LABEL": "0x1564",
				"TYPE": "KeyWait"
			},
			{
				"LABEL": "0x1566",
				"TYPE": "MoveChar",
				"U32": [
					45,
					1,
					1
				]
			},
			{
				"LABEL": "0x157a",
				"TYPE": "NewPage"
			},
			{
				"LABEL": "0x157c",
				"TYPE": "Text",
				"STRING": [
					"【ファル】",
					"「……」"
				]
			},
			{
				"LABEL": "0x158e",
				"TYPE": "KeyWait"
			},
			{
				"LABEL": "0x1590",
				"TYPE": "NewPage"
			},
			{
				"LABEL": "0x1592",
				"TYPE": "Text",
				"STRING": [
					"無言で立ちつくす彼女に、僕は笑顔で最後に言う。"
				]
			},
			{
				"LABEL": "0x159a",
				"TYPE": "KeyWait"
			},
			{
				"LABEL": "0x159c",
				"TYPE": "SEPlay",
				"U32": [
					33
				]
			},
			{
				"LABEL": "0x15a4",
				"TYPE": "NewPage"
			},
			{
				"LABEL": "0x15a6",
				"TYPE": "Text",
				"STRING": [
					"【クリス】",
					"「また明日」"
				]
			},
			{
				"LABEL": "0x15b8",
				"TYPE": "KeyWait"
			},
			{
				"LABEL": "0x15ba",
				"TYPE": "NewPage"
			},
			{
				"LABEL": "0x15bc",
				"TYPE": "Text",
				"STRING": [
					"やや遅れて、ファルさんの控えめな笑顔とともに返事が",
					"あった。"
				]
			},
			{
				"LABEL": "0x15ce",
				"TYPE": "KeyWait"
			},
			{
				"LABEL": "0x15d0",
				"TYPE": "MoveChar",
				"U32": [
					40,
					1,
					1
				]
			},
			{
				"LABEL": "0x15e4",
				"TYPE": "NewPage"
			},
			{
				"LABEL": "0x15e6",
				"TYPE": "Voice",
				"U32": [
					144044
				]
			},
			{
				"LABEL": "0x15ee",
				"TYPE": "Text",
				"STRING": [
					"【ファル】",
					"「また明日」"
				]
			},
			{
				"LABEL": "0x1600",
				"TYPE": "KeyWait"
			},
			{
				"LABEL": "0x1602",
				"TYPE": "SEPlay",
				"U32": [
					34
				]
			},
			{
				"LABEL": "0x160a",
				"TYPE": "AllHideChar"
			},
			{
				"LABEL": "0x160c",
				"TYPE": "BGMStop"
			},
			{
				"LABEL": "0x160e",
				"TYPE": "TextHide"
			},
			{
				"LABEL": "0x1610",
				"TYPE": "BlackOut",
				"U32": [
					1
				]
			},
			{
				"LABEL": "0x1618",
				"TYPE": "SkipDisable",
				"U32": [
					1
				]
			},
			{
				"LABEL": "0x1620",
				"TYPE": "Wait",
				"U32": [
					1000
				]
			},
			{
				"LABEL": "0x1628",
				"TYPE": "SCNCHG",
				"U32": [
					0
				]
			},
			{
				"LABEL": "0x1630",
				"TYPE": "JMP",
				"JUMP_TO_LABEL": "0x1636"
			},
			{
				"LABEL": "0x1636",
				"TYPE": "RET",
				"U32": [
					0
				]
			}
		]
	]
}